reddit_sauce_harvester/__init__.py
reddit_sauce_harvester/__main__.py
reddit_sauce_harvester/harvester.py
reddit_sauce_harvester/meta.py
reddit_sauce_harvester/reddit_api.py
reddit_sauce_harvester/utils.py
reddit_sauce_harvester/cli/__init__.py
reddit_sauce_harvester-0.1.0.dist-info/LICENSE.txt
reddit_sauce_harvester-0.1.0.dist-info/METADATA
reddit_sauce_harvester-0.1.0.dist-info/WHEEL
reddit_sauce_harvester-0.1.0.dist-info/entry_points.txt
reddit_sauce_harvester-0.1.0.dist-info/top_level.txt
reddit_sauce_harvester-0.1.0.dist-info/RECORD
