Metadata-Version: 2.1
Name: reddit-sauce-harvester
Version: 0.1.0
Summary: My package description
Home-page: https://github.com/mehq/reddit-sauce-harvester
Author: Mezbaul Haque
Author-email: mezba109@gmail.com
License: Unlicense
Keywords: reddit
Platform: any
Classifier: Environment :: Console
Classifier: License :: OSI Approved :: The Unlicense (Unlicense)
Classifier: Programming Language :: Python
Classifier: Programming Language :: Python :: 3
Classifier: Programming Language :: Python :: 3 :: Only
Classifier: Topic :: Terminals
Requires-Python: <4,>=3.6
License-File: LICENSE.txt
Requires-Dist: click (==8.1.2)
Requires-Dist: requests (==2.27.1)
